[
    {
        "id": 260978,
        "name": "Barrier!!",
        "collector_number": "OP04-095",
        "rarity": "Common",
        "expansion_id": 3487,
        "expansion_name": "OP-04: Kingdoms of Intrigue Promos",
        "image_url": ""
    },
    {
        "id": 260982,
        "name": "Charlotte Moscato",
        "collector_number": "OP04-108",
        "rarity": "Uncommon",
        "expansion_id": 3487,
        "expansion_name": "OP-04: Kingdoms of Intrigue Promos",
        "image_url": ""
    },
    {
        "id": 261008,
        "name": "The Weak Do Not Have the Right to Choose How They Die!!!",
        "collector_number": "OP04-038",
        "rarity": "Common",
        "expansion_id": 3487,
        "expansion_name": "OP-04: Kingdoms of Intrigue Promos",
        "image_url": ""
    },
    {
        "id": 261024,
        "name": "Pound",
        "collector_number": "OP04-110",
        "rarity": "Common",
        "expansion_id": 3487,
        "expansion_name": "OP-04: Kingdoms of Intrigue Promos",
        "image_url": ""
    },
    {
        "id": 260977,
        "name": "Bananagator",
        "collector_number": "OP04-062",
        "rarity": "Common",
        "expansion_id": 3487,
        "expansion_name": "OP-04: Kingdoms of Intrigue Promos",
        "image_url": ""
    },
    {
        "id": 261019,
        "name": "Queen",
        "collector_number": "OP04-046",
        "rarity": "Uncommon",
        "expansion_id": 3487,
        "expansion_name": "OP-04: Kingdoms of Intrigue Promos",
        "image_url": ""
    },
    {
        "id": 260994,
        "name": "Donquixote Family",
        "collector_number": "OP04-036",
        "rarity": "Common",
        "expansion_id": 3487,
        "expansion_name": "OP-04: Kingdoms of Intrigue Promos",
        "image_url": ""
    },
    {
        "id": 261007,
        "name": "Tom",
        "collector_number": "OP04-061",
        "rarity": "Common",
        "expansion_id": 3487,
        "expansion_name": "OP-04: Kingdoms of Intrigue Promos",
        "image_url": ""
    },
    {
        "id": 261015,
        "name": "Rabiyan",
        "collector_number": "OP04-113",
        "rarity": "Common",
        "expansion_id": 3487,
        "expansion_name": "OP-04: Kingdoms of Intrigue Promos",
        "image_url": ""
    },
    {
        "id": 261016,
        "name": "Randolph",
        "collector_number": "OP04-114",
        "rarity": "Common",
        "expansion_id": 3487,
        "expansion_name": "OP-04: Kingdoms of Intrigue Promos",
        "image_url": ""
    },
    {
        "id": 260986,
        "name": "Chinjao",
        "collector_number": "OP04-086",
        "rarity": "Common",
        "expansion_id": 3487,
        "expansion_name": "OP-04: Kingdoms of Intrigue Promos",
        "image_url": ""
    },
    {
        "id": 261009,
        "name": "Otama",
        "collector_number": "OP04-097",
        "rarity": "Common",
        "expansion_id": 3487,
        "expansion_name": "OP-04: Kingdoms of Intrigue Promos",
        "image_url": ""
    },
    {
        "id": 260983,
        "name": "Charlotte Perospero",
        "collector_number": "OP04-107",
        "rarity": "Common",
        "expansion_id": 3487,
        "expansion_name": "OP-04: Kingdoms of Intrigue Promos",
        "image_url": ""
    },
    {
        "id": 261017,
        "name": "Rokki",
        "collector_number": "OP04-054",
        "rarity": "Common",
        "expansion_id": 3487,
        "expansion_name": "OP-04: Kingdoms of Intrigue Promos",
        "image_url": ""
    },
    {
        "id": 260979,
        "name": "Black Maria",
        "collector_number": "OP04-052",
        "rarity": "Common",
        "expansion_id": 3487,
        "expansion_name": "OP-04: Kingdoms of Intrigue Promos",
        "image_url": ""
    },
    {
        "id": 261002,
        "name": "Tony Tony.Chopper",
        "collector_number": "OP04-010",
        "rarity": "Common",
        "expansion_id": 3487,
        "expansion_name": "OP-04: Kingdoms of Intrigue Promos",
        "image_url": ""
    },
    {
        "id": 261011,
        "name": "Super Spot-Billed Duck Troops",
        "collector_number": "OP04-009",
        "rarity": "Uncommon",
        "expansion_id": 3487,
        "expansion_name": "OP-04: Kingdoms of Intrigue Promos",
        "image_url": ""
    },
    {
        "id": 261018,
        "name": "Mr.4(Babe)",
        "collector_number": "OP04-071",
        "rarity": "Uncommon",
        "expansion_id": 3487,
        "expansion_name": "OP-04: Kingdoms of Intrigue Promos",
        "image_url": ""
    },
    {
        "id": 261021,
        "name": "Hanger",
        "collector_number": "OP04-050",
        "rarity": "Common",
        "expansion_id": 3487,
        "expansion_name": "OP-04: Kingdoms of Intrigue Promos",
        "image_url": ""
    },
    {
        "id": 261006,
        "name": "Toko",
        "collector_number": "OP04-098",
        "rarity": "Uncommon",
        "expansion_id": 3487,
        "expansion_name": "OP-04: Kingdoms of Intrigue Promos",
        "image_url": ""
    },
    {
        "id": 260992,
        "name": "Gun Modoki",
        "collector_number": "OP04-115",
        "rarity": "Common",
        "expansion_id": 3487,
        "expansion_name": "OP-04: Kingdoms of Intrigue Promos",
        "image_url": ""
    },
    {
        "id": 261004,
        "name": "Tonoyasu",
        "collector_number": "OP04-109",
        "rarity": "Common",
        "expansion_id": 3487,
        "expansion_name": "OP-04: Kingdoms of Intrigue Promos",
        "image_url": ""
    },
    {
        "id": 260991,
        "name": "Gyats",
        "collector_number": "OP04-080",
        "rarity": "Uncommon",
        "expansion_id": 3487,
        "expansion_name": "OP-04: Kingdoms of Intrigue Promos",
        "image_url": ""
    },
    {
        "id": 260985,
        "name": "Corrida Coliseum",
        "collector_number": "OP04-096",
        "rarity": "Common",
        "expansion_id": 3487,
        "expansion_name": "OP-04: Kingdoms of Intrigue Promos",
        "image_url": ""
    },
    {
        "id": 261012,
        "name": "Yokozuna",
        "collector_number": "OP04-068",
        "rarity": "Common",
        "expansion_id": 3487,
        "expansion_name": "OP-04: Kingdoms of Intrigue Promos",
        "image_url": ""
    },
    {
        "id": 260976,
        "name": "Baby 5",
        "collector_number": "OP04-032",
        "rarity": "Uncommon",
        "expansion_id": 3487,
        "expansion_name": "OP-04: Kingdoms of Intrigue Promos",
        "image_url": ""
    },
    {
        "id": 260984,
        "name": "Daddy Masterson",
        "collector_number": "OP04-027",
        "rarity": "Common",
        "expansion_id": 3487,
        "expansion_name": "OP-04: Kingdoms of Intrigue Promos",
        "image_url": ""
    },
    {
        "id": 261003,
        "name": "Trafalgar Law",
        "collector_number": "OP04-087",
        "rarity": "Common",
        "expansion_id": 3487,
        "expansion_name": "OP-04: Kingdoms of Intrigue Promos",
        "image_url": ""
    },
    {
        "id": 260998,
        "name": "Dragon Twister Demolition Breath",
        "collector_number": "OP04-057",
        "rarity": "Uncommon",
        "expansion_id": 3487,
        "expansion_name": "OP-04: Kingdoms of Intrigue Promos",
        "image_url": ""
    },
    {
        "id": 260995,
        "name": "Eric",
        "collector_number": "OP04-022",
        "rarity": "Uncommon",
        "expansion_id": 3487,
        "expansion_name": "OP-04: Kingdoms of Intrigue Promos",
        "image_url": ""
    },
    {
        "id": 261020,
        "name": "Mr.13 & Ms.Friday",
        "collector_number": "OP04-073",
        "rarity": "Common",
        "expansion_id": 3487,
        "expansion_name": "OP-04: Kingdoms of Intrigue Promos",
        "image_url": ""
    },
    {
        "id": 261005,
        "name": "Stussy",
        "collector_number": "OP04-084",
        "rarity": "Common",
        "expansion_id": 3487,
        "expansion_name": "OP-04: Kingdoms of Intrigue Promos",
        "image_url": ""
    },
    {
        "id": 260981,
        "name": "Charlotte Bavarois",
        "collector_number": "OP04-106",
        "rarity": "Common",
        "expansion_id": 3487,
        "expansion_name": "OP-04: Kingdoms of Intrigue Promos",
        "image_url": ""
    },
    {
        "id": 260999,
        "name": "Viola",
        "collector_number": "OP04-021",
        "rarity": "Common",
        "expansion_id": 3487,
        "expansion_name": "OP-04: Kingdoms of Intrigue Promos",
        "image_url": ""
    },
    {
        "id": 260997,
        "name": "Enchanting Vertigo Dance",
        "collector_number": "OP04-018",
        "rarity": "Uncommon",
        "expansion_id": 3487,
        "expansion_name": "OP-04: Kingdoms of Intrigue Promos",
        "image_url": ""
    },
    {
        "id": 260988,
        "name": "Giolla",
        "collector_number": "OP04-025",
        "rarity": "Common",
        "expansion_id": 3487,
        "expansion_name": "OP-04: Kingdoms of Intrigue Promos",
        "image_url": ""
    },
    {
        "id": 261001,
        "name": "Usopp",
        "collector_number": "OP04-003",
        "rarity": "Uncommon",
        "expansion_id": 3487,
        "expansion_name": "OP-04: Kingdoms of Intrigue Promos",
        "image_url": ""
    },
    {
        "id": 261014,
        "name": "Sasaki",
        "collector_number": "OP04-048",
        "rarity": "Uncommon",
        "expansion_id": 3487,
        "expansion_name": "OP-04: Kingdoms of Intrigue Promos",
        "image_url": ""
    },
    {
        "id": 261023,
        "name": "Mr.3(Galdino)",
        "collector_number": "OP04-070",
        "rarity": "Uncommon",
        "expansion_id": 3487,
        "expansion_name": "OP-04: Kingdoms of Intrigue Promos",
        "image_url": ""
    },
    {
        "id": 261022,
        "name": "Plague Rounds",
        "collector_number": "OP04-055",
        "rarity": "Common",
        "expansion_id": 3487,
        "expansion_name": "OP-04: Kingdoms of Intrigue Promos",
        "image_url": ""
    },
    {
        "id": 260987,
        "name": "Diable Jambe Joue Shot",
        "collector_number": "OP04-116",
        "rarity": "Uncommon",
        "expansion_id": 3487,
        "expansion_name": "OP-04: Kingdoms of Intrigue Promos",
        "image_url": ""
    },
    {
        "id": 260975,
        "name": "Apis",
        "collector_number": "OP04-041",
        "rarity": "Common",
        "expansion_id": 3487,
        "expansion_name": "OP-04: Kingdoms of Intrigue Promos",
        "image_url": ""
    },
    {
        "id": 261000,
        "name": "Weakness...Is an Unforgivable Sin.",
        "collector_number": "OP04-076",
        "rarity": "Common",
        "expansion_id": 3487,
        "expansion_name": "OP-04: Kingdoms of Intrigue Promos",
        "image_url": ""
    },
    {
        "id": 260990,
        "name": "Hajrudin",
        "collector_number": "OP04-088",
        "rarity": "Uncommon",
        "expansion_id": 3487,
        "expansion_name": "OP-04: Kingdoms of Intrigue Promos",
        "image_url": ""
    },
    {
        "id": 260993,
        "name": "Dellinger",
        "collector_number": "OP04-029",
        "rarity": "Common",
        "expansion_id": 3487,
        "expansion_name": "OP-04: Kingdoms of Intrigue Promos",
        "image_url": ""
    },
    {
        "id": 260980,
        "name": "Carmel",
        "collector_number": "OP04-101",
        "rarity": "Common",
        "expansion_id": 3487,
        "expansion_name": "OP-04: Kingdoms of Intrigue Promos",
        "image_url": ""
    },
    {
        "id": 261010,
        "name": "Suleiman",
        "collector_number": "OP04-085",
        "rarity": "Uncommon",
        "expansion_id": 3487,
        "expansion_name": "OP-04: Kingdoms of Intrigue Promos",
        "image_url": ""
    },
    {
        "id": 260996,
        "name": "Flapping Thread",
        "collector_number": "OP04-037",
        "rarity": "Uncommon",
        "expansion_id": 3487,
        "expansion_name": "OP-04: Kingdoms of Intrigue Promos",
        "image_url": ""
    },
    {
        "id": 261013,
        "name": "Sanji",
        "collector_number": "OP04-007",
        "rarity": "Common",
        "expansion_id": 3487,
        "expansion_name": "OP-04: Kingdoms of Intrigue Promos",
        "image_url": ""
    },
    {
        "id": 261025,
        "name": "Kuro",
        "collector_number": "OP04-023",
        "rarity": "Common",
        "expansion_id": 3487,
        "expansion_name": "OP-04: Kingdoms of Intrigue Promos",
        "image_url": ""
    },
    {
        "id": 264359,
        "name": "Boodle",
        "collector_number": "OP03-050",
        "rarity": "Uncommon",
        "expansion_id": 3487,
        "expansion_name": "OP-04: Kingdoms of Intrigue Promos",
        "image_url": ""
    },
    {
        "id": 264370,
        "name": "Kingdoms of Intrigue: Dash Pack",
        "collector_number": "N/A",
        "rarity": "Unknown",
        "expansion_id": 3487,
        "expansion_name": "OP-04: Kingdoms of Intrigue Promos",
        "image_url": ""
    },
    {
        "id": 261038,
        "name": "Ipponmatsu",
        "collector_number": "OP04-042",
        "rarity": "Common",
        "expansion_id": 3487,
        "expansion_name": "OP-04: Kingdoms of Intrigue Promos",
        "image_url": ""
    },
    {
        "id": 261039,
        "name": "Happiness Punch",
        "collector_number": "OP04-017",
        "rarity": "Common",
        "expansion_id": 3487,
        "expansion_name": "OP-04: Kingdoms of Intrigue Promos",
        "image_url": ""
    },
    {
        "id": 264363,
        "name": "Speed Jil",
        "collector_number": "OP03-006",
        "rarity": "Common",
        "expansion_id": 3487,
        "expansion_name": "OP-04: Kingdoms of Intrigue Promos",
        "image_url": ""
    },
    {
        "id": 264362,
        "name": "Shirahoshi",
        "collector_number": "OP03-116",
        "rarity": "Uncommon",
        "expansion_id": 3487,
        "expansion_name": "OP-04: Kingdoms of Intrigue Promos",
        "image_url": ""
    },
    {
        "id": 261032,
        "name": "Nefeltari Cobra",
        "collector_number": "OP04-012",
        "rarity": "Common",
        "expansion_id": 3487,
        "expansion_name": "OP-04: Kingdoms of Intrigue Promos",
        "image_url": ""
    },
    {
        "id": 261048,
        "name": "Ice Oni",
        "collector_number": "OP04-047",
        "rarity": "Common",
        "expansion_id": 3487,
        "expansion_name": "OP-04: Kingdoms of Intrigue Promos",
        "image_url": ""
    },
    {
        "id": 264360,
        "name": "Kalifa",
        "collector_number": "OP03-081",
        "rarity": "Rare",
        "expansion_id": 3487,
        "expansion_name": "OP-04: Kingdoms of Intrigue Promos",
        "image_url": ""
    },
    {
        "id": 261040,
        "name": "Mr.2.Bon.Kurei(Bentham)",
        "collector_number": "OP04-069",
        "rarity": "Common",
        "expansion_id": 3487,
        "expansion_name": "OP-04: Kingdoms of Intrigue Promos",
        "image_url": ""
    },
    {
        "id": 261044,
        "name": "Kung Fu Jugon",
        "collector_number": "OP04-005",
        "rarity": "Common",
        "expansion_id": 3487,
        "expansion_name": "OP-04: Kingdoms of Intrigue Promos",
        "image_url": ""
    },
    {
        "id": 261047,
        "name": "Karoo",
        "collector_number": "OP04-004",
        "rarity": "Common",
        "expansion_id": 3487,
        "expansion_name": "OP-04: Kingdoms of Intrigue Promos",
        "image_url": ""
    },
    {
        "id": 261034,
        "name": "Nez-Palm Cannon",
        "collector_number": "OP04-075",
        "rarity": "Uncommon",
        "expansion_id": 3487,
        "expansion_name": "OP-04: Kingdoms of Intrigue Promos",
        "image_url": ""
    },
    {
        "id": 261041,
        "name": "Miss.MerryChristmas(Drophy)",
        "collector_number": "OP04-067",
        "rarity": "Common",
        "expansion_id": 3487,
        "expansion_name": "OP-04: Kingdoms of Intrigue Promos",
        "image_url": ""
    },
    {
        "id": 264358,
        "name": "Buggy",
        "collector_number": "OP03-032",
        "rarity": "Common",
        "expansion_id": 3487,
        "expansion_name": "OP-04: Kingdoms of Intrigue Promos",
        "image_url": ""
    },
    {
        "id": 261033,
        "name": "Jack",
        "collector_number": "OP04-049",
        "rarity": "Uncommon",
        "expansion_id": 3487,
        "expansion_name": "OP-04: Kingdoms of Intrigue Promos",
        "image_url": ""
    },
    {
        "id": 261026,
        "name": "Miss.Goldenweek(Marianne)",
        "collector_number": "OP04-065",
        "rarity": "Common",
        "expansion_id": 3487,
        "expansion_name": "OP-04: Kingdoms of Intrigue Promos",
        "image_url": ""
    },
    {
        "id": 261031,
        "name": "Lao.G",
        "collector_number": "OP04-034",
        "rarity": "Uncommon",
        "expansion_id": 3487,
        "expansion_name": "OP-04: Kingdoms of Intrigue Promos",
        "image_url": ""
    },
    {
        "id": 261029,
        "name": "Oimo & Kashii",
        "collector_number": "OP04-078",
        "rarity": "Common",
        "expansion_id": 3487,
        "expansion_name": "OP-04: Kingdoms of Intrigue Promos",
        "image_url": ""
    },
    {
        "id": 261036,
        "name": "Iceburg",
        "collector_number": "OP04-059",
        "rarity": "Uncommon",
        "expansion_id": 3487,
        "expansion_name": "OP-04: Kingdoms of Intrigue Promos",
        "image_url": ""
    },
    {
        "id": 261046,
        "name": "Ideo",
        "collector_number": "OP04-077",
        "rarity": "Common",
        "expansion_id": 3487,
        "expansion_name": "OP-04: Kingdoms of Intrigue Promos",
        "image_url": ""
    },
    {
        "id": 264361,
        "name": "Monkey.D.Luffy",
        "collector_number": "OP03-070",
        "rarity": "Rare",
        "expansion_id": 3487,
        "expansion_name": "OP-04: Kingdoms of Intrigue Promos",
        "image_url": ""
    },
    {
        "id": 261043,
        "name": "Leo",
        "collector_number": "OP04-091",
        "rarity": "Uncommon",
        "expansion_id": 3487,
        "expansion_name": "OP-04: Kingdoms of Intrigue Promos",
        "image_url": ""
    },
    {
        "id": 261028,
        "name": "Page One",
        "collector_number": "OP04-053",
        "rarity": "Uncommon",
        "expansion_id": 3487,
        "expansion_name": "OP-04: Kingdoms of Intrigue Promos",
        "image_url": ""
    },
    {
        "id": 261042,
        "name": "Machvise",
        "collector_number": "OP04-033",
        "rarity": "Uncommon",
        "expansion_id": 3487,
        "expansion_name": "OP-04: Kingdoms of Intrigue Promos",
        "image_url": ""
    },
    {
        "id": 261030,
        "name": "Koza",
        "collector_number": "OP04-006",
        "rarity": "Uncommon",
        "expansion_id": 3487,
        "expansion_name": "OP-04: Kingdoms of Intrigue Promos",
        "image_url": ""
    },
    {
        "id": 268773,
        "name": "Kingdoms of Intrigue | Pre-Release Pack",
        "collector_number": "N/A",
        "rarity": "Unknown",
        "expansion_id": 3487,
        "expansion_name": "OP-04: Kingdoms of Intrigue Promos",
        "image_url": ""
    },
    {
        "id": 261045,
        "name": "Kouzuki Hiyori",
        "collector_number": "OP04-103",
        "rarity": "Uncommon",
        "expansion_id": 3487,
        "expansion_name": "OP-04: Kingdoms of Intrigue Promos",
        "image_url": ""
    },
    {
        "id": 261049,
        "name": "Hera",
        "collector_number": "OP04-111",
        "rarity": "Uncommon",
        "expansion_id": 3487,
        "expansion_name": "OP-04: Kingdoms of Intrigue Promos",
        "image_url": ""
    },
    {
        "id": 261027,
        "name": "Orlumbus",
        "collector_number": "OP04-079",
        "rarity": "Common",
        "expansion_id": 3487,
        "expansion_name": "OP-04: Kingdoms of Intrigue Promos",
        "image_url": ""
    },
    {
        "id": 261035,
        "name": "Nami",
        "collector_number": "OP04-011",
        "rarity": "Common",
        "expansion_id": 3487,
        "expansion_name": "OP-04: Kingdoms of Intrigue Promos",
        "image_url": ""
    }
]